zama/__init__.py
zama/file.py
zama-0.0.1.dist-info/LICENSE
zama-0.0.1.dist-info/METADATA
zama-0.0.1.dist-info/WHEEL
zama-0.0.1.dist-info/top_level.txt
zama-0.0.1.dist-info/RECORD
