Metadata-Version: 2.1
Name: zama
Version: 0.0.1
Summary: Zama homomorphic execution framework
Home-page: https://zama.ai
Author: Zama Team
Author-email: hello@zama.ai
License: UNKNOWN
Platform: UNKNOWN
Classifier: Programming Language :: Python :: 3
Classifier: License :: OSI Approved :: GNU General Public License v3 (GPLv3)
Classifier: Operating System :: OS Independent
Requires-Python: >=3.6
